xbrief/__init__.py
xbrief/deco/__init__.py
xbrief/deco/deco_entries/__init__.py
xbrief/deco/deco_entries/deco_entries.py
xbrief/deco/deco_json/__init__.py
xbrief/deco/deco_matrix/__init__.py
xbrief/deco/deco_node/__init__.py
xbrief/deco/deco_node/helpers/__init__.py
xbrief/deco/deco_node/helpers/mutate_key_pad.py
xbrief/deco/deco_node/preset/__init__.py
xbrief/deco/deco_node/render/__init__.py
xbrief/deco/deco_node/render/render_entries.py
xbrief/deco/deco_node/render/render_string.py
xbrief/deco/deco_node/render/render_vector.py
xbrief/deco/deco_str/__init__.py
xbrief/deco/deco_vector/__init__.py
xbrief/deco/deco_vector/deco_vector.py
xbrief/logger/__init__.py
xbrief/logger/logger.py
xbrief/margin/__init__.py
xbrief/margin/entries_margin/__init__.py
xbrief/margin/matrix_margin/__init__.py
xbrief/margin/matrix_margin/matrix_margin.py
xbrief/margin/matrix_margin/sizing.py
xbrief/margin/utils/__init__.py
xbrief/margin/vector_margin/__init__.py
xbrief/margin/vector_margin/marginize.py
xbrief/margin/vector_margin/sizing.py
xbrief/margin/vector_margin/vector_margin.py
xbrief/padder/__init__.py
xbrief/padder/pad_entries/__init__.py
xbrief/padder/pad_keyed_column/__init__.py
xbrief/padder/pad_matrix/__init__.py
xbrief/padder/pad_string/__init__.py
xbrief/padder/pad_table/__init__.py
xbrief/padder/pad_vector/__init__.py
xbrief-0.0.6.dist-info/LICENSE
xbrief-0.0.6.dist-info/WHEEL
xbrief-0.0.6.dist-info/METADATA
xbrief-0.0.6.dist-info/RECORD
